pytest_csv/__init__.py
pytest_csv/_hooks.py
pytest_csv/_plugin.py
pytest_csv/_reporter.py
pytest_csv/column/__init__.py
pytest_csv/column/_builtin.py
pytest_csv/column/_ids.py
pytest_csv/column/_registry.py
pytest_csv/column/_status.py
pytest_csv/column/_utils.py
pytest_csv-3.0.0.dist-info/COPYING
pytest_csv-3.0.0.dist-info/METADATA
pytest_csv-3.0.0.dist-info/WHEEL
pytest_csv-3.0.0.dist-info/entry_points.txt
pytest_csv-3.0.0.dist-info/top_level.txt
pytest_csv-3.0.0.dist-info/RECORD
