Metadata-Version: 2.1
Name: pytest-csv
Version: 3.0.0
Summary: CSV output for pytest.
Home-page: https://github.com/nicoulaj/pytest-csv
Author: Julien Nicoulaud
Author-email: julien.nicoulaud@gmail.com
License: GPLv3
Keywords: py.test pytest csv tsv report
Platform: UNKNOWN
Classifier: Framework :: Pytest
Classifier: Operating System :: Microsoft :: Windows
Classifier: Operating System :: MacOS :: MacOS X
Classifier: Operating System :: POSIX
Classifier: Operating System :: Unix
Classifier: Programming Language :: Python
Classifier: Programming Language :: Python :: 3
Classifier: Programming Language :: Python :: 3.6
Classifier: Programming Language :: Python :: 3.7
Classifier: Programming Language :: Python :: 3.8
Classifier: Programming Language :: Python :: 3.9
Classifier: Programming Language :: Python :: Implementation :: CPython
Classifier: Programming Language :: Python :: Implementation :: PyPy
Classifier: License :: OSI Approved :: GNU General Public License (GPL)
Provides-Extra: test
